gdrivedataset/__init__.py
gdrivedataset/loader.py
gdrive_dataset-0.0.6.dist-info/METADATA
gdrive_dataset-0.0.6.dist-info/WHEEL
gdrive_dataset-0.0.6.dist-info/top_level.txt
gdrive_dataset-0.0.6.dist-info/RECORD
